cf_data_tracker/__init__.py
cf_data_tracker/clean_tracker.py
cf_data_tracker/pipeline_alert.py
cf_data_tracker/raw_tracker.py
cf_data_tracker/utils.py
cf_data_tracker-0.3.19.dist-info/LICENSE
cf_data_tracker-0.3.19.dist-info/METADATA
cf_data_tracker-0.3.19.dist-info/WHEEL
cf_data_tracker-0.3.19.dist-info/top_level.txt
cf_data_tracker-0.3.19.dist-info/RECORD
