Metadata-Version: 2.1
Name: cf_data_tracker
Version: 0.3.19
Summary: A package for managing raw and clean data tracker operations
Author: Rami, R. K
Author-email: ramireddykowaluru@gmail.com
Classifier: Development Status :: 3 - Alpha
Classifier: Intended Audience :: Developers
Classifier: License :: OSI Approved :: MIT License
Classifier: Programming Language :: Python :: 3
Classifier: Programming Language :: Python :: 3.11
Requires-Python: >=3.9
License-File: LICENSE
Requires-Dist: boto3
Requires-Dist: python-dotenv
Requires-Dist: beautifulsoup4
Requires-Dist: botocore
Requires-Dist: bs4
Requires-Dist: certifi
Requires-Dist: charset-normalizer
Requires-Dist: idna
Requires-Dist: jmespath
Requires-Dist: python-dateutil
Requires-Dist: requests
Requires-Dist: s3transfer ==0.10.0
Requires-Dist: six
Requires-Dist: soupsieve
Requires-Dist: urllib3
